devtools_random_string/__init__.py
devtools_random_string-1.0.1.dist-info/METADATA
devtools_random_string-1.0.1.dist-info/WHEEL
devtools_random_string-1.0.1.dist-info/top_level.txt
devtools_random_string-1.0.1.dist-info/RECORD
