Metadata-Version: 2.1
Name: devtools-random-string
Version: 1.0.1
Summary: Random string generator
Home-page: https://devtools.at/tools/random-string
Author: DevTools.at
Author-email: hello@devtools.at
Project-URL: Homepage, https://devtools.at/tools/random-string
Project-URL: Repository, https://github.com/devtools-at/random-string
Classifier: Development Status :: 4 - Beta
Classifier: Intended Audience :: Developers
Classifier: License :: OSI Approved :: MIT License
Classifier: Programming Language :: Python :: 3
Requires-Python: >=3.8
